solfinder/MCDM.py
solfinder/__init__.py
solfinder-1.0.4.dist-info/COPYING
solfinder-1.0.4.dist-info/COPYING.LESSER
solfinder-1.0.4.dist-info/METADATA
solfinder-1.0.4.dist-info/WHEEL
solfinder-1.0.4.dist-info/top_level.txt
solfinder-1.0.4.dist-info/RECORD
