Metadata-Version: 2.1
Name: solfinder
Version: 1.0.4
Summary: SolFinder 1.0.4
Home-page: UNKNOWN
Author: fcastino
Author-email: f.castino@tudelft.nl
License: GNU LGPLv3
Platform: UNKNOWN
License-File: COPYING
License-File: COPYING.LESSER
